motleycoder/__init__.py
motleycoder/codemap/__init__.py
motleycoder/codemap/builtins_by_lang.json
motleycoder/codemap/file_group.py
motleycoder/codemap/graph.py
motleycoder/codemap/map_args.py
motleycoder/codemap/parse.py
motleycoder/codemap/rank.py
motleycoder/codemap/render.py
motleycoder/codemap/repomap.py
motleycoder/codemap/tag.py
motleycoder/linter.py
motleycoder/prompts.py
motleycoder/queries/README.md
motleycoder/queries/tree-sitter-c-tags.scm
motleycoder/queries/tree-sitter-c_sharp-tags.scm
motleycoder/queries/tree-sitter-cpp-tags.scm
motleycoder/queries/tree-sitter-elisp-tags.scm
motleycoder/queries/tree-sitter-elixir-tags.scm
motleycoder/queries/tree-sitter-elm-tags.scm
motleycoder/queries/tree-sitter-go-tags.scm
motleycoder/queries/tree-sitter-java-tags.scm
motleycoder/queries/tree-sitter-javascript-tags.scm
motleycoder/queries/tree-sitter-ocaml-tags.scm
motleycoder/queries/tree-sitter-php-tags.scm
motleycoder/queries/tree-sitter-python-tags.scm
motleycoder/queries/tree-sitter-ql-tags.scm
motleycoder/queries/tree-sitter-r-tags.scm
motleycoder/queries/tree-sitter-ruby-tags.scm
motleycoder/queries/tree-sitter-rust-tags.scm
motleycoder/queries/tree-sitter-typescript-tags.scm
motleycoder/repo.py
motleycoder/tools/__init__.py
motleycoder/tools/add_files_tool.py
motleycoder/tools/file_edit_tool.py
motleycoder/tools/get_full_text_tool.py
motleycoder/tools/get_modifiable_files_tool.py
motleycoder/tools/inspect_entity_tool.py
motleycoder/tools/return_to_user_tool.py
motleycoder/user_interface.py
motleycoder-0.1.0.dist-info/LICENSE
motleycoder-0.1.0.dist-info/METADATA
motleycoder-0.1.0.dist-info/WHEEL
motleycoder-0.1.0.dist-info/RECORD
