Metadata-Version: 2.1
Name: motleycoder
Version: 0.1.0
Summary: A set of tools for building AI coders
Author: MotleyCrew
Author-email: github@motleycrew.ai
Requires-Python: >=3.10,<=3.13
Classifier: Programming Language :: Python :: 3
Classifier: Programming Language :: Python :: 3.10
Classifier: Programming Language :: Python :: 3.11
Classifier: Programming Language :: Python :: 3.12
Requires-Dist: GitPython (>=3.1.43,<4.0.0)
Requires-Dist: diskcache (>=5.6.3,<6.0.0)
Requires-Dist: flake8 (>=7.1.1,<8.0.0)
Requires-Dist: grep-ast (>=0.3.3,<0.4.0)
Requires-Dist: litellm (>=1.44.5,<2.0.0)
Requires-Dist: motleycrew (>=0.1.12,<0.2.0)
Requires-Dist: networkx (>=3.3,<4.0)
Requires-Dist: rich (>=13.7.1,<14.0.0)
Requires-Dist: tree-sitter (==0.21.3)
Requires-Dist: tree-sitter-languages (>=1.10.2,<2.0.0)
